StrongLIA/__init__.py
StrongLIA/models.py
StrongLIA/optimization.py
StrongLIA/data/__init__.py
StrongLIA/test/__init__.py
StrongLIA-0.1.dist-info/LICENSE.txt
StrongLIA-0.1.dist-info/METADATA
StrongLIA-0.1.dist-info/WHEEL
StrongLIA-0.1.dist-info/top_level.txt
StrongLIA-0.1.dist-info/RECORD
